reportgen/__init__.py
reportgen/analysis.py
reportgen/config.py
reportgen/delaunay.py
reportgen/questionnaire.py
reportgen/report.py
reportgen/associate/__init__.py
reportgen/associate/fpgrowth.py
reportgen/font/DroidSansFallback.ttf
reportgen/font/readme.txt
reportgen/images/logo.png
reportgen/questionnaire/__init__.py
reportgen/questionnaire/questionnaire.py
reportgen/template/template.pptx
reportgen/utils/__init__.py
reportgen/utils/delaunay.py
reportgen/utils/metrics.py
reportgen/utils/preprocessing.py
reportgen/utils/utils.py
reportgen-0.1.8.dist-info/DESCRIPTION.rst
reportgen-0.1.8.dist-info/METADATA
reportgen-0.1.8.dist-info/RECORD
reportgen-0.1.8.dist-info/WHEEL
reportgen-0.1.8.dist-info/metadata.json
reportgen-0.1.8.dist-info/top_level.txt
