Metadata-Version: 1.1
Name: reportgen
Version: 0.1.8
Summary: reportgen is a Python library for creating and updating analysis report.
Home-page: https://github.com/gasongjian/reportgen
Author: JSong
Author-email: gasongjian@126.com
License: BSD License
Platform: all
Classifier: Development Status :: 4 - Beta
Classifier: Intended Audience :: Developers
Classifier: License :: OSI Approved :: BSD License
Classifier: Programming Language :: Python
Classifier: Programming Language :: Python :: Implementation
Classifier: Programming Language :: Python :: 3.4
Classifier: Programming Language :: Python :: 3.5
Classifier: Programming Language :: Python :: 3.6
Classifier: Topic :: Software Development :: Libraries
